admin_sso/__init__.py
admin_sso/admin.py
admin_sso/apps.py
admin_sso/auth.py
admin_sso/default_settings.py
admin_sso/models.py
admin_sso/views.py
admin_sso/migrations/0001_initial.py
admin_sso/migrations/__init__.py
admin_sso/templates/admin_sso/login.html
django_admin_sso-5.2.0.dist-info/AUTHORS
django_admin_sso-5.2.0.dist-info/LICENSE
django_admin_sso-5.2.0.dist-info/METADATA
django_admin_sso-5.2.0.dist-info/WHEEL
django_admin_sso-5.2.0.dist-info/top_level.txt
django_admin_sso-5.2.0.dist-info/RECORD
