Metadata-Version: 2.1
Name: django-admin-sso
Version: 5.2.0
Summary: Django SSO solution
Home-page: http://github.com/matthiask/django-admin-sso/
Author: Marc Egli
Author-email: egli@allink.ch
License: BSD License
Platform: OS Independent
Classifier: Development Status :: 5 - Production/Stable
Classifier: Environment :: Web Environment
Classifier: Framework :: Django
Classifier: Intended Audience :: Developers
Classifier: License :: OSI Approved :: BSD License
Classifier: Operating System :: OS Independent
Classifier: Programming Language :: Python
Classifier: Topic :: Internet :: WWW/HTTP :: Dynamic Content
Requires-Python: >=3.8
License-File: LICENSE
License-File: AUTHORS
Requires-Dist: Django (>=3.2)
Requires-Dist: oauth2client (>=1.2)
